genarena/__init__.py
genarena-0.0.1.dist-info/METADATA
genarena-0.0.1.dist-info/WHEEL
genarena-0.0.1.dist-info/top_level.txt
genarena-0.0.1.dist-info/RECORD
