Metadata-Version: 2.4
Name: genarena
Version: 0.0.1
Summary: genarena
Author-email: genarena <genarena@example.com>
License: MIT
Project-URL: Homepage, https://github.com/genarena/genarena
Classifier: Development Status :: 1 - Planning
Classifier: Programming Language :: Python :: 3
Classifier: License :: OSI Approved :: MIT License
Requires-Python: >=3.7
